{"id":"270","title":"如皋佛学会小引","translator":"","summary":"","part":"卷四 · 杂著","segments":[{"o":"世出世间事，若具热心毅力，决无不成。邓子璞君，前为募建金陵法云寺大殿，立四十八愿捐册，手题其额曰，有愿必成。且为标其大意。未久而其愿果满。苏州陆西林，年逾八旬，家不甚丰，慨任一愿，随即交清。洵足为成就善举者之模范。","t":"世间、出世间的事，如果具有热心毅力，绝无不成就的。邓子璞居士，以前为募建南京法云寺大殿，立下四十八愿捐册，手写捐册的名称为：有愿必成。而且标出其中的大意。不久，他的愿望果然圆满。苏州的陆西林居士，年过八十，家中不是很富有，慷慨任捐一个大愿，随即交清。实在足以作为成就善举之人的模范。"},{"o":"今阅如皋马塘佛学会章程，并闻承办之朱季等居士，悉皆认真净修，而且力求撙节。当年经费仅需五百元。现虽入会者只数十人，但能广引会员，则人捐二元，自可无虞。况尚听人纳八元六元四元乎。","t":"现今阅读如皋县马塘佛学会的章程，并听到承办佛学会的朱季等居士，全都认真净修，而且力求节俭。当年的经费仅需五百元。现在虽然入会的人只有数十人，但只要能广泛引入会员，那么每人捐出二元钱，自然就会无所忧虑。何况还听说有人交纳八元、六元、四元呢？"},{"o":"彼法云殿二千元一愿，尚得即满。况此区区数元，兼有征信清册，年终报告。谁不乐于入会，以期亲沐佛化。现生为清净三业之善人，临终作高登九品之圣众。有愿必成，敢为创办与修持者保任焉。","t":"那法云寺大殿，二千元一个大愿，尚且得以圆满。何况这区区数元，而且又有征信清册，年终报告。谁不乐意加入佛学会，以期亲身沐浴佛陀教化。现生成为清净三业的善人，临终作高登九品的圣众。有愿必成，我大胆地为创办佛学会与修持的人做个担保。"},{"o":"【注释】"},{"n":1,"note":"【撙节】节省；节约。"},{"n":2,"note":"【当年】就在本年；同一年。"},{"n":3,"note":"【无虞】没有忧患，太平无事。"},{"n":4,"note":"【清册】详细登记有关项目的册子。将财、物或有关项目清理后详细登记的册子。"},{"n":5,"note":"【保任】担保。"}]}