{"id":"042","title":"复王慎斋居士书（民国二十年）","translator":"","summary":"","part":"卷上 · 书","segments":[{"o":"赵冷姑之夫，弃妻恋妓，于世情论，为冷姑之命薄不幸，依佛法论之，实为大幸。若夫不见弃，则夫妻情爱，儿女纠缠，终日劳碌，便难念佛求生西方矣。","t":"赵冷姑的丈夫，抛弃妻子，贪恋妓女，于世间人情来说，是冷姑的命薄不幸，但从佛法上来看，实在是大幸。如果冷姑不被抛弃，那么夫妻情爱，儿女纠缠，整天劳碌，就很难念佛求生西方了。"},{"o":"今因夫弃，而得以专心念佛，将使临命终时，蒙佛接引，即便了生脱死，超凡入圣矣。其得益全在夫弃上，切诫勿生怨恨，当生感激。","t":"现在因为丈夫抛弃她，而能够专心念佛，将来在她临命终时，蒙佛接引，就可以了生脱死，超凡入圣了！她能得到这个利益完全是因为丈夫的抛弃，所以千万不要生起怨恨心，应该生起感激心。"},{"o":"又当以己念佛功德，为其夫回向，令其速出迷途，早寻觉路。有此心肠，则爱憎二心，均不得而生，更能得念佛之大效矣。","t":"还应当把她自己念佛的功德，为她丈夫回向，使他尽快出离迷途，早日找到觉悟之路。有这个想法，那么恩爱憎恨二种心，都不会生起，那就更能得到念佛的巨大实效了。"},{"o":"今为彼取法名为慧冰，谓其居心，当如冰清洁，了无尘累也。宜将前炼丹运气之法，完全丢却，一心念佛，求生西方，则可不虚此生此遇矣。","t":"现在为她取法名为慧冰，是说她的存心，应当如冰一样清洁，没有一点尘累。应该将以前炼丹运气的方法，完全丢掉，一心念佛，求生西方，那么就不会虚度此生，不会错过这个机遇了！"},{"o":"其念佛之法则，能看书，则令彼看嘉言录，及浅近等书。否则，为彼说其大略。现在国运危岌，天灾人祸，相继而作，宜令一切人同念佛号，及观世音号，以为预防之计。","t":"念佛的法则，能够看书的话，就让她看《嘉言录》，以及道理浅近的佛学书籍。否则，就为她说说其中的大意。现在国运危急，天灾人祸，相继而来，应该让一切人一起念佛号，以及观世音菩萨圣号，作为预防灾祸的方法。"}]}