{"id": "jy-037", "volume": "jy", "volumeName": "嘉言录", "juan": "附录", "category": "", "title": "二、东林佛号的唱念要领", "translator": "", "summary": "", "segments": [{"orig": ["东林佛号以八字特质为方针，语速低沉缓慢，格调哀亮，内具深信切愿之情怀，四句形成一个结构组。", "第一句的重音放在“南无”上，一心归命。要唱出在生死旷野寻求佛力救度的渴望。", "第二句的重音放在“阿弥”上，在苦苦寻求中，历经难险，终于找到了南无的对象，就是阿弥陀佛。要唱出寻找到阿弥陀佛的欢欣。", "第三句的重音放在“陀”上，当我们归命于阿弥陀佛时，觉了原来阿弥陀佛与我竟是同体，我在弥陀心中念佛，弥陀在我心中呼应加持。要唱出弥陀与我同体同源的欣慰。", "第四句的重音又放在“阿弥”上，当觉了阿弥陀佛与我同体时，回光反照，原来我自性即是阿弥陀佛“无量光寿”。要唱出自性弥陀的自信自肯。由归命到归元。", "这样，第一句向外部的渴望寻找，到第四句向内心安稳的回归，形成东林佛号四句一组的音声结构，四句佛号不断循环。", "唱念的音声抑扬结构掌握后，加之两个配合：", "（一）佛号与步点的配合。一句佛号走四步，“南无”一步（迈右脚），“阿弥”一步（迈左脚），“陀”一步（迈右脚）， “佛”一步（迈左脚）。随法器音声节奏，走准四个步点。", "（二）佛号与呼吸的配合。中间停顿时，深吸气到腹部，脐轮发音，一口气将佛号念完，浑融一体。", "如是持念，久久便能唱出东林佛号的韵味，悲欣交集，香光庄严。伏冀念佛同仁共勉。"], "trans": [], "notes": []}], "anomalies": []}