{"id":"q600-449","volume":"q600","volumeName":"印光法师答念佛600问","juan":"卷八 · 净土法门与至诚行持","category":"第四章 · 念佛功课与仪轨、方法","title":"449、念佛记数的作用是什么？怎么记数？","translator":"","summary":"记数是为防懈惰，无懈惰之心不记亦可。印祖记数念佛之法，最能摄心。","segments":[{"orig":["念佛记数，是防懈惰。如无懈惰之心，不记亦可。记数也可不用掐珠子。最初当用珠子念一点钟。以后快慢，照此一样，念一刻、半点、一点，均可知其佛数。又《文钞》中记数念佛之法，最能摄心。阅之自知。"],"trans":["（七）念佛记数，是防止懈惰。如果没有懈惰之心，不记数也可以。记数，也可不用掐珠子记数。最初应当用珠子念一个钟头。以后的快慢速度，照这个样子，念一刻钟，半个钟头，一个钟头，就都可以知道念佛的数量了。另外，《文钞》中的十念记数念佛之法，最能摄心。读了自然知道。"],"notes":[],"src":"（《新编全本印光法师文钞》卷二十二第191页 复传度和尚书）"}],"anomalies":[]}