{"id": "sb2-064", "volume": "sb2", "volumeName": "三编 · 下册", "juan": "卷三 · 书三", "category": "", "title": "复林赞华居士书七", "translator": "", "summary": "", "segments": [{"orig": ["讲经，岂必年讲一经，不可重复乎。然则日日吃饭，何不厌其重复耶。", "心经义理渊深，初机何由得益。纵有所得，亦只解路。何如净土法门之即闻即可实行乎。即行愿品，亦不必定要讲多日。佛以六百卷大般若之蕴奥，以二百六十字发挥无遗。岂必要钩枝延蔓，只取广多以逞口辩乎。", "道绰禅师乃出格高僧，专弘净土。寿七十余岁，一生讲净土三经近二百遍。即二十岁讲，五十多年，年须二三次方可。", "彻悟语录与一居士书云，一夏两终楞严。何畏行愿文长，而非七日所了乎。七日过促，或作十日。讲经岂定规要任讲者尽量东拉西扯，不在肯綮处指点乎。", "汝之知见，是知涉博而不知守约。欲以博益初机，则是门庭建设中事。共君一夜话，胜读十年书，愈病不在驴驼药，皆守约之古训也。", "然现今战事发生，后来之事，不可逆料。当令一切老幼男女，同念阿弥陀佛，并念观世音菩萨。以祈生免灾祸，死归乐邦。", "讲经尚非当务之急。所急宜布告一切老幼男女，同念观世音菩萨。至于平定后讲经，尤当以初机净土之正信为先。", "倪商勤，施立谦，既知皈依，各为各起法名。倪商勤法名宗勤。念佛求生西方，自行化他，须以勤为本。若懒惰懈怠，则难克有成矣。", "施立谦法名宗谦。谦则不自满足，如海纳百川，空含万象。种种罪业，由谦而消。种种功德，由谦而成。今为汝与彼二人寄净土十要一包，祈为分与。", "光老矣，目力精神均不给，以后不许常来信。但按十要所说而修，又何所欠，而欲常问乎。", "若不以净土专修为事，欲遍通教义，亦非一函二函之所能得其目的也。祈慧察。十要一书，为净宗至要之书。且勿作好高务胜之计画，便可得至高至胜之利益。一函遍复，亦人人当务之急。"], "trans": ["讲经，哪里是一年只能讲一部经，不能重复讲呢？然而每天吃饭，为什么就不厌倦重复呢？", "《心经》的义理深奥，初学人哪有那么容易受益。即使有所受益，也只是在解释方面而已。哪像净土法门，即刻听闻就能即刻实行呢？即使是《行愿品》，也不必一定要讲很多天。佛将六百卷大般若的深蕴奥义，用二百六十字的《心经》发挥无遗。哪里必定要发枝生蔓，只取广博繁多来逞口舌之辩呢？", "道绰禅师，是位杰出的高僧，专门弘扬净土法门。世寿七十多岁，一生讲净土三经将近二百遍。即使从二十岁开始讲，五十多年，一年必须要讲二三遍才能做到。", "《彻悟禅师语录》中给一位居士的信写道：一个夏天，讲完两遍《楞严经》。何必害怕《行愿品》的经文长，而无法七天讲完呢？如果觉得七天太过仓促，或者作十天讲。讲经哪会一定要让讲经的人尽量东拉西扯，而不在重要之处指点呢？", "你的知见，是只知道要涉及广博而不知道遵守简约。想以广博来利益初学，这是宗派门庭建设中的事。“共君一夜话，胜读十年书”，“愈病不在驴驼药”，都是遵守简约的古训啊。", "然而现今战争发生，将来的事，无法预料。应当让一切老幼男女，同念阿弥陀佛，并念观世音菩萨。以祈求活着的时候免于灾祸，死后归于极乐莲邦。", "讲经还不是当务之急。所急的应该是告知一切老幼男女，同念观世音菩萨。至于战争平息之后讲经，尤其应当以初学人对净土的正信为先。", "倪商勤，施立谦，既然知道要皈依，现分别为他们起法名。倪商勤法名宗勤。念佛求生西方，自行化他，必须以精勤为本。如果懒惰懈怠，就很难有所成就。", "施立谦法名宗谦。谦就不会自我满足，如同大海容纳百川，虚空包含万象。种种罪业，由谦卑而消除。种种功德，由谦卑而成就。现在为你和他们二人寄《净土十要》一包，请你分给他们。", "我老了，视力精神都不足，以后不许常来信。只要按《十要》中所说的去修行，还会有什么欠缺，而要常常来问我的呢？", "如果不以净土专修为事务，却想要遍通教义，这样也不是一封、二封信所能达到目的的。请智慧思察。《十要》这本书，是净宗最重要的书籍。千万不要作好高务胜的计划，就能得到最高最殊胜的利益。《一函遍复》，也是人人要知道的当务之急。"], "notes": [{"n": 1, "term": "肯綮", "text": "1.筋骨结合的地方。2.比喻要害或最重要的关键。"}, {"n": 2, "term": "守约", "text": "简易可行。"}, {"n": 3, "term": "门庭建设", "text": "意谓佛门宗师接引度化初学佛的人，所使用的方便机法。"}, {"n": 4, "term": "驴驼药", "text": "大慧普觉禅师的《宗门武库》中说：“瘥病不假驴驼药，若是对病与药，篱根下拾得一茎草，便可疗病，说什么朱砂、附子、人参、白术。”驴驼常与“马载”同用，故“驴驼药”意谓以驴马驼载一大车的药材。"}]}], "anomalies": []}